<?xml version="1.0" encoding="utf-8"?>
<Document>
  <Engineering version="V17" />
  <DocumentInfo>
    <Created>2025-08-05T09:35:59.1568817Z</Created>
    <ExportSetting>WithDefaults</ExportSetting>
    <InstalledProducts>
      <Product>
        <DisplayName>Totally Integrated Automation Portal</DisplayName>
        <DisplayVersion>V17</DisplayVersion>
      </Product>
      <OptionPackage>
        <DisplayName>TIA Portal Openness</DisplayName>
        <DisplayVersion>V17</DisplayVersion>
      </OptionPackage>
      <OptionPackage>
        <DisplayName>TIA Portal Version Control Interface</DisplayName>
        <DisplayVersion>V17</DisplayVersion>
      </OptionPackage>
      <Product>
        <DisplayName>SINAMICS Startdrive Advanced</DisplayName>
        <DisplayVersion>V17</DisplayVersion>
      </Product>
      <OptionPackage>
        <DisplayName>SINAMICS Startdrive G130, G150, S120, S150, SINAMICS MV, S210</DisplayName>
        <DisplayVersion>V17</DisplayVersion>
      </OptionPackage>
      <OptionPackage>
        <DisplayName>SINAMICS Startdrive G110M, G120, G120C, G120D, G120P, G115D</DisplayName>
        <DisplayVersion>V17</DisplayVersion>
      </OptionPackage>
      <Product>
        <DisplayName>STEP 7 Professional</DisplayName>
        <DisplayVersion>V17</DisplayVersion>
      </Product>
      <OptionPackage>
        <DisplayName>STEP 7 Safety</DisplayName>
        <DisplayVersion>V17</DisplayVersion>
      </OptionPackage>
      <Product>
        <DisplayName>WinCC Advanced</DisplayName>
        <DisplayVersion>V17</DisplayVersion>
      </Product>
    </InstalledProducts>
  </DocumentInfo>
  <SW.Tags.PlcTagTable ID="0">
    <AttributeList>
      <Name>Default tag table</Name>
    </AttributeList>
    <ObjectList>
      <SW.Tags.PlcTag ID="1" CompositionName="Tags">
        <AttributeList>
          <DataTypeName>Bool</DataTypeName>
          <ExternalAccessible>true</ExternalAccessible>
          <ExternalVisible>true</ExternalVisible>
          <ExternalWritable>true</ExternalWritable>
          <LogicalAddress>%M0.0</LogicalAddress>
          <Name>Start_Seq</Name>
        </AttributeList>
        <ObjectList>
          <MultilingualText ID="2" CompositionName="Comment">
            <ObjectList>
              <MultilingualTextItem ID="3" CompositionName="Items">
                <AttributeList>
                  <Culture>en-US</Culture>
                  <Text />
                </AttributeList>
              </MultilingualTextItem>
              <MultilingualTextItem ID="4" CompositionName="Items">
                <AttributeList>
                  <Culture>de-DE</Culture>
                  <Text />
                </AttributeList>
              </MultilingualTextItem>
            </ObjectList>
          </MultilingualText>
        </ObjectList>
      </SW.Tags.PlcTag>
      <SW.Tags.PlcTag ID="5" CompositionName="Tags">
        <AttributeList>
          <DataTypeName>Bool</DataTypeName>
          <ExternalAccessible>true</ExternalAccessible>
          <ExternalVisible>true</ExternalVisible>
          <ExternalWritable>true</ExternalWritable>
          <LogicalAddress>%M0.1</LogicalAddress>
          <Name>Rob_Reset_1</Name>
        </AttributeList>
        <ObjectList>
          <MultilingualText ID="6" CompositionName="Comment">
            <ObjectList>
              <MultilingualTextItem ID="7" CompositionName="Items">
                <AttributeList>
                  <Culture>en-US</Culture>
                  <Text />
                </AttributeList>
              </MultilingualTextItem>
              <MultilingualTextItem ID="8" CompositionName="Items">
                <AttributeList>
                  <Culture>de-DE</Culture>
                  <Text />
                </AttributeList>
              </MultilingualTextItem>
            </ObjectList>
          </MultilingualText>
        </ObjectList>
      </SW.Tags.PlcTag>
      <SW.Tags.PlcTag ID="9" CompositionName="Tags">
        <AttributeList>
          <DataTypeName>Bool</DataTypeName>
          <ExternalAccessible>true</ExternalAccessible>
          <ExternalVisible>true</ExternalVisible>
          <ExternalWritable>true</ExternalWritable>
          <LogicalAddress>%M0.2</LogicalAddress>
          <Name>Rob_Reset_2</Name>
        </AttributeList>
        <ObjectList>
          <MultilingualText ID="A" CompositionName="Comment">
            <ObjectList>
              <MultilingualTextItem ID="B" CompositionName="Items">
                <AttributeList>
                  <Culture>en-US</Culture>
                  <Text />
                </AttributeList>
              </MultilingualTextItem>
              <MultilingualTextItem ID="C" CompositionName="Items">
                <AttributeList>
                  <Culture>de-DE</Culture>
                  <Text />
                </AttributeList>
              </MultilingualTextItem>
            </ObjectList>
          </MultilingualText>
        </ObjectList>
      </SW.Tags.PlcTag>
      <SW.Tags.PlcTag ID="D" CompositionName="Tags">
        <AttributeList>
          <DataTypeName>Bool</DataTypeName>
          <ExternalAccessible>true</ExternalAccessible>
          <ExternalVisible>true</ExternalVisible>
          <ExternalWritable>true</ExternalWritable>
          <LogicalAddress>%M0.3</LogicalAddress>
          <Name>RA_CC_1</Name>
        </AttributeList>
        <ObjectList>
          <MultilingualText ID="E" CompositionName="Comment">
            <ObjectList>
              <MultilingualTextItem ID="F" CompositionName="Items">
                <AttributeList>
                  <Culture>en-US</Culture>
                  <Text />
                </AttributeList>
              </MultilingualTextItem>
              <MultilingualTextItem ID="10" CompositionName="Items">
                <AttributeList>
                  <Culture>de-DE</Culture>
                  <Text />
                </AttributeList>
              </MultilingualTextItem>
            </ObjectList>
          </MultilingualText>
        </ObjectList>
      </SW.Tags.PlcTag>
      <SW.Tags.PlcUserConstant ID="11" CompositionName="UserConstants">
        <AttributeList>
          <DataTypeName>Int</DataTypeName>
          <Name>GRP_JOB_NAME_SIZE</Name>
          <Value>50</Value>
        </AttributeList>
        <ObjectList>
          <MultilingualText ID="12" CompositionName="Comment">
            <ObjectList>
              <MultilingualTextItem ID="13" CompositionName="Items">
                <AttributeList>
                  <Culture>en-US</Culture>
                  <Text>String site group and job name</Text>
                </AttributeList>
              </MultilingualTextItem>
              <MultilingualTextItem ID="14" CompositionName="Items">
                <AttributeList>
                  <Culture>de-DE</Culture>
                  <Text>String Größe Gruppen- und Jobnamen</Text>
                </AttributeList>
              </MultilingualTextItem>
            </ObjectList>
          </MultilingualText>
        </ObjectList>
      </SW.Tags.PlcUserConstant>
      <SW.Tags.PlcUserConstant ID="15" CompositionName="UserConstants">
        <AttributeList>
          <DataTypeName>DInt</DataTypeName>
          <Name>MAX_CNT_GRP_OVR_ENTRIES</Name>
          <Value>100</Value>
        </AttributeList>
        <ObjectList>
          <MultilingualText ID="16" CompositionName="Comment">
            <ObjectList>
              <MultilingualTextItem ID="17" CompositionName="Items">
                <AttributeList>
                  <Culture>en-US</Culture>
                  <Text>Maximum number of groups in the group overview</Text>
                </AttributeList>
              </MultilingualTextItem>
              <MultilingualTextItem ID="18" CompositionName="Items">
                <AttributeList>
                  <Culture>de-DE</Culture>
                  <Text>Maximale Anzahl Gruppen in der Gruppen-Übersicht</Text>
                </AttributeList>
              </MultilingualTextItem>
            </ObjectList>
          </MultilingualText>
        </ObjectList>
      </SW.Tags.PlcUserConstant>
      <SW.Tags.PlcUserConstant ID="19" CompositionName="UserConstants">
        <AttributeList>
          <DataTypeName>DInt</DataTypeName>
          <Name>MAX_CNT_MTN_OVR_ENTRIES</Name>
          <Value>150</Value>
        </AttributeList>
        <ObjectList>
          <MultilingualText ID="1A" CompositionName="Comment">
            <ObjectList>
              <MultilingualTextItem ID="1B" CompositionName="Items">
                <AttributeList>
                  <Culture>en-US</Culture>
                  <Text>Maximum number of motions in the motion overview</Text>
                </AttributeList>
              </MultilingualTextItem>
              <MultilingualTextItem ID="1C" CompositionName="Items">
                <AttributeList>
                  <Culture>de-DE</Culture>
                  <Text>Maximale Anzahl Motions in der Motion-Übersicht</Text>
                </AttributeList>
              </MultilingualTextItem>
            </ObjectList>
          </MultilingualText>
        </ObjectList>
      </SW.Tags.PlcUserConstant>
    </ObjectList>
  </SW.Tags.PlcTagTable>
</Document>